cockroach_poker-0.1.3.data/scripts/cockroach-host
cockroach_poker-0.1.3.data/scripts/cockroach-player
cockroachpoker/__init__.py
cockroachpoker/encrypted_message.py
cockroachpoker/game.py
cockroachpoker/signed_message.py
cockroach_poker-0.1.3.dist-info/LICENSE
cockroach_poker-0.1.3.dist-info/METADATA
cockroach_poker-0.1.3.dist-info/WHEEL
cockroach_poker-0.1.3.dist-info/top_level.txt
cockroach_poker-0.1.3.dist-info/RECORD
