Metadata-Version: 2.1
Name: cockroach-poker
Version: 0.1.3
Summary: A fun card game all about bluffing
Home-page: https://gitlab.com/oldironhorse/cockroach-poker
Author: Simon Redding
Author-email: s1m0n.r3dd1ng@gmail.com
License: UNKNOWN
Platform: UNKNOWN
Requires-Python: >=3.5
Requires-Dist: pycryptodome
Requires-Dist: paho-mqtt
Requires-Dist: click
